setup.cfg
setup.py
fauxtograph/__init__.py
fauxtograph/fauxto.py
fauxtograph/fauxtograph.py
fauxtograph/vaegan.py
fauxtograph.egg-info/PKG-INFO
fauxtograph.egg-info/SOURCES.txt
fauxtograph.egg-info/dependency_links.txt
fauxtograph.egg-info/entry_points.txt
fauxtograph.egg-info/requires.txt
fauxtograph.egg-info/top_level.txt