Metadata-Version: 1.1
Name: fauxtograph
Version: 1.0.3
Summary: Python module for training unsupervised deep, generative models on images.
Home-page: https://github.com/stitchfix/fauxtograph
Author: TJ Torres
Author-email: ttorres@mit.edu
License: MIT
Keywords: unsupervised,images,deep learning,neural networks,Chainer
Platform: UNKNOWN
Classifier: Development Status :: 4 - Beta
Classifier: Intended Audience :: Developers
Classifier: Programming Language :: Python :: 2
Classifier: Programming Language :: Python :: 2.6
Classifier: Programming Language :: Python :: 2.7
Classifier: Programming Language :: Python :: 3.4
